chronolog_service/__init__.py
chronolog_service/tracker.py
chronolog_service-1.0.5.dist-info/METADATA
chronolog_service-1.0.5.dist-info/WHEEL
chronolog_service-1.0.5.dist-info/top_level.txt
chronolog_service-1.0.5.dist-info/RECORD
