Metadata-Version: 2.4
Name: chronolog_service
Version: 1.0.5
Summary: Chronolog: Log microservice version to Redis at startup
Home-page: https://github.com/yourusername/chronolog
Author: Lucas Simopoulos
Author-email: lucas@loopcv.com
Classifier: Development Status :: 4 - Beta
Classifier: Intended Audience :: Developers
Classifier: License :: OSI Approved :: MIT License
Classifier: Programming Language :: Python :: 3
Requires-Python: >=3.7
Requires-Dist: redis>=4.0.0
Dynamic: author
Dynamic: author-email
Dynamic: classifier
Dynamic: description
Dynamic: description-content-type
Dynamic: home-page
Dynamic: requires-dist
Dynamic: requires-python
Dynamic: summary
